LICENSE
README.md
setup.py
telebotapi/__init__.py
telebotapi/chats.py
telebotapi/daemon.py
telebotapi/entities.py
telebotapi/exceptions.py
telebotapi/files.py
telebotapi/messages.py
telebotapi/telebotapi.py
telebotapi/update.py
telebotapi.egg-info/PKG-INFO
telebotapi.egg-info/SOURCES.txt
telebotapi.egg-info/dependency_links.txt
telebotapi.egg-info/top_level.txt