Metadata-Version: 2.1
Name: telebotapi
Version: 0.9.9.3
Summary: A telegram bot api for telegram, with asynchronous polling
Home-page: https://github.com/topongo/telebotapi
Author: Lorenzo Bodini
Author-email: lorenzo.bodini.private@gmail.com
License: GPL3
Requires-Python: >=3.6
License-File: LICENSE
